mkdocs_windmillex/404.html
mkdocs_windmillex/__init__.py
mkdocs_windmillex/article-nav.html
mkdocs_windmillex/base.html
mkdocs_windmillex/main.html
mkdocs_windmillex/nav-item.html
mkdocs_windmillex/nav-pane.html
mkdocs_windmillex/search.html
mkdocs_windmillex/topbar.html
mkdocs_windmillex/css/base.css
mkdocs_windmillex/css/bootstrap-3.3.7.css
mkdocs_windmillex/css/bootstrap-3.3.7.min.css
mkdocs_windmillex/css/font-awesome-4.7.0.css
mkdocs_windmillex/css/font-awesome-4.7.0.min.css
mkdocs_windmillex/css/highlight.css
mkdocs_windmillex/fonts/fontawesome-webfont.eot
mkdocs_windmillex/fonts/fontawesome-webfont.svg
mkdocs_windmillex/fonts/fontawesome-webfont.ttf
mkdocs_windmillex/fonts/fontawesome-webfont.woff
mkdocs_windmillex/fonts/fontawesome-webfont.woff2
mkdocs_windmillex/fonts/glyphicons-halflings-regular.eot
mkdocs_windmillex/fonts/glyphicons-halflings-regular.svg
mkdocs_windmillex/fonts/glyphicons-halflings-regular.ttf
mkdocs_windmillex/fonts/glyphicons-halflings-regular.woff
mkdocs_windmillex/fonts/glyphicons-halflings-regular.woff2
mkdocs_windmillex/img/favicon.ico
mkdocs_windmillex/js/base.js
mkdocs_windmillex/js/bootstrap-3.3.7.js
mkdocs_windmillex/js/bootstrap-3.3.7.min.js
mkdocs_windmillex/js/elasticlunr.js
mkdocs_windmillex/js/elasticlunr.min.js
mkdocs_windmillex/js/highlight.pack.js
mkdocs_windmillex/js/jquery-3.2.1.js
mkdocs_windmillex/js/jquery-3.2.1.min.js
mkdocs_windmillex/js/lunr.jp.js
mkdocs_windmillex/js/lunr.stemmer.support.js
mkdocs_windmillex/js/tinyseg.js
mkdocs_windmillex-0.0.1.dist-info/DESCRIPTION.rst
mkdocs_windmillex-0.0.1.dist-info/METADATA
mkdocs_windmillex-0.0.1.dist-info/RECORD
mkdocs_windmillex-0.0.1.dist-info/WHEEL
mkdocs_windmillex-0.0.1.dist-info/entry_points.txt
mkdocs_windmillex-0.0.1.dist-info/metadata.json
mkdocs_windmillex-0.0.1.dist-info/top_level.txt
