Metadata-Version: 2.0
Name: mkdocs-windmillex
Version: 0.0.1
Summary: MkDocs theme focused on navigation and usability
Home-page: https://github.com/guenbakku/mkdocs-windmillex
Author: UNKNOWN
Author-email: UNKNOWN
License: MIT
Platform: UNKNOWN
